raytraverse/__init__.py
raytraverse/api.py
raytraverse/cli.py
raytraverse/cli_funcs.py
raytraverse/de432_2020s.bsp
raytraverse/raytu.py
raytraverse/evaluate/__init__.py
raytraverse/evaluate/fieldmetric.py
raytraverse/evaluate/multilummetricset.py
raytraverse/evaluate/samplingmetrics.py
raytraverse/formatter/__init__.py
raytraverse/formatter/formatter.py
raytraverse/formatter/radianceformatter.py
raytraverse/integrator/__init__.py
raytraverse/integrator/helpers.py
raytraverse/integrator/integrator.py
raytraverse/integrator/sensorintegrator.py
raytraverse/lightfield/__init__.py
raytraverse/lightfield/lightfield.py
raytraverse/lightfield/lightplanekd.py
raytraverse/lightfield/lightresult.py
raytraverse/lightfield/sensorplanekd.py
raytraverse/lightfield/sets.py
raytraverse/lightfield/sunsensorplanekd.py
raytraverse/lightfield/sunsplanekd.py
raytraverse/lightfield/zonallightresult.py
raytraverse/lightpoint/__init__.py
raytraverse/lightpoint/compressedpointkd.py
raytraverse/lightpoint/lightpointkd.py
raytraverse/lightpoint/srcviewpoint.py
raytraverse/mapper/__init__.py
raytraverse/mapper/maskedplanmapper.py
raytraverse/mapper/planmapper.py
raytraverse/mapper/skymapper.py
raytraverse/renderer/__init__.py
raytraverse/renderer/imagerenderer.py
raytraverse/renderer/rcontrib.py
raytraverse/renderer/rtrace.py
raytraverse/renderer/sprenderer.py
raytraverse/sampler/__init__.py
raytraverse/sampler/basesampler.py
raytraverse/sampler/draw.py
raytraverse/sampler/imagesampler.py
raytraverse/sampler/isamplerarea.py
raytraverse/sampler/isamplersuns.py
raytraverse/sampler/samplerarea.py
raytraverse/sampler/samplerpt.py
raytraverse/sampler/samplersuns.py
raytraverse/sampler/sensor.py
raytraverse/sampler/skysamplerpt.py
raytraverse/sampler/srcsamplerpt.py
raytraverse/sampler/srcsamplerptview.py
raytraverse/sampler/sunsamplerpt.py
raytraverse/sampler/sunsamplerptview.py
raytraverse/scene/__init__.py
raytraverse/scene/basescene.py
raytraverse/scene/imagescene.py
raytraverse/scene/scene.py
raytraverse-1.4.4.dist-info/LICENSE
raytraverse-1.4.4.dist-info/METADATA
raytraverse-1.4.4.dist-info/WHEEL
raytraverse-1.4.4.dist-info/entry_points.txt
raytraverse-1.4.4.dist-info/top_level.txt
raytraverse-1.4.4.dist-info/RECORD
