Metadata-Version: 2.1
Name: raytraverse
Version: 1.4.4
Summary: adaptive sampling for CBDM
Home-page: https://github.com/stephanwaz/raytraverse
Author: Stephen Wasilewski
Author-email: stephanwaz@gmail.com
License: Mozilla Public License 2.0 (MPL 2.0)
Keywords: raytraverse
Classifier: Development Status :: 2 - Pre-Alpha
Classifier: License :: OSI Approved :: Mozilla Public License 2.0 (MPL 2.0)
Classifier: Natural Language :: English
Classifier: Programming Language :: Python :: 3.7
Classifier: Programming Language :: Python :: 3.8
Classifier: Programming Language :: Python :: 3.9
Classifier: Programming Language :: Python :: 3.10
Requires-Python: >=3.7
License-File: LICENSE
Requires-Dist: craytraverse>=0.1.5
Requires-Dist: raytools
Requires-Dist: clasp
Requires-Dist: numpy<1.27
Requires-Dist: scipy
Requires-Dist: matplotlib
Requires-Dist: skyfield
Requires-Dist: shapely
Requires-Dist: scikit-learn
